filetagslib/__init__.py
filetagslib/filetagslib.py
filetagslib/filetagslib_test.py
filetagslib-2019.12.14.1.dist-info/LICENSE.txt
filetagslib-2019.12.14.1.dist-info/METADATA
filetagslib-2019.12.14.1.dist-info/WHEEL
filetagslib-2019.12.14.1.dist-info/top_level.txt
filetagslib-2019.12.14.1.dist-info/RECORD
